standalorm/__init__.py
standalorm/cli.py
standalorm/db_makers.py
standalorm/LICENSE.md
standalorm/manage.py
standalorm/models_template.py
standalorm/orm-settings.toml
standalorm/orm_init.py
standalorm/settings.py
standalorm/utils.py
standalorm-1.0.0.dist-info/entry_points.txt
standalorm-1.0.0.dist-info/LICENSE.md
standalorm-1.0.0.dist-info/WHEEL
standalorm-1.0.0.dist-info/METADATA
standalorm-1.0.0.dist-info/RECORD
