Metadata-Version: 2.1
Name: standalorm
Version: 1.0.0
Summary: A Python library that enables you to harness the power of Django's ORM in standalone Python scripts.
Home-page: https://github.com/jasonalantolbert/standalorm
License: MIT
Keywords: django,orm,standalone
Author: Jason Tolbert
Author-email: jasonalantolbert@gmail.com
Requires-Python: >=3.9.0,<4.0.0
Classifier: License :: OSI Approved :: MIT License
Classifier: Programming Language :: Python :: 3
Classifier: Programming Language :: Python :: 3.9
Requires-Dist: Django (>=3.1.5,<4.0.0)
Requires-Dist: click (>=7.1.2,<8.0.0)
Requires-Dist: colorama (>=0.4.4,<0.5.0)
Requires-Dist: dj-database-url (>=0.5.0,<0.6.0)
Requires-Dist: path (>=15.0.1,<16.0.0)
Requires-Dist: pathvalidate (>=2.3.2,<3.0.0)
Requires-Dist: toml (>=0.10.2,<0.11.0)
Project-URL: Documentation, https://standalorm.readthedocs.io
